shiertier_os/__init__.py
shiertier_os/os.py
shiertier_os-0.0.3.dist-info/LICENSE
shiertier_os-0.0.3.dist-info/METADATA
shiertier_os-0.0.3.dist-info/WHEEL
shiertier_os-0.0.3.dist-info/top_level.txt
shiertier_os-0.0.3.dist-info/RECORD
